Workbook

Sheet Read Me
A1: NIKE | GEN Z INDIA — FINANCIAL MODEL
A3: Purpose | B3: Illustrative financial case model to assess a proposed Gen Z market-expansion campaign in India. Independent student portfolio case; not commissioned by or affiliated with Nike.
A5: How to use
A7: 1 | B7: Open the Inputs sheet and choose Downside, Base or Upside from the scenario dropdown in cell B3.
A8: 2 | B8: Edit the yellow input cells only to change reach, funnel rates, order value, margins and campaign investment.
A9: 3 | B9: Review Scenario Analysis to compare the three cases and Dashboard for the selected scenario.
A10: 4 | B10: Use 12-Month Model to review how reach, orders, revenue and contribution are phased over the year.
A11: 5 | B11: Use Sensitivity to test how changes in reach and purchase conversion affect net contribution after campaign spend.
A13: Model logic | B13: Reach × engagement rate = engaged audience; engaged audience × visit rate = site visits; site visits × purchase conversion = first orders. Revenue = orders × average order value. Contribution = revenue × contribution margin. Net contribution after campaign = contribution − campaign investment.
A15: Important interpretation | B15: All values are illustrative planning assumptions, not Nike actuals, forecasts, validated market data, or promised results. The model estimates campaign-attributed incremental orders for scenario planning; it does not prove incrementality or account for all corporate overhead, taxes, working capital, cannibalization, or long-term brand effects.
A17: Contribution margin | B17: Gross margin less incremental variable costs (e.g., payment, fulfilment, returns/service allowances). Contribution is not net profit or EBITDA.
A19: Break-even | B19: Break-even orders = campaign investment ÷ contribution per order. This is the order volume required to recover campaign investment on a contribution basis.
A21: Currency / period | B21: Indian rupees (INR); annual scenario view with a 12-month phasing schedule.
A23: Portfolio disclosure | B23: This is a hypothetical consulting case study using public market context and transparent assumptions. No Nike internal data was accessed.

Sheet Inputs
A1: INPUTS & ASSUMPTIONS
A3: Selected scenario | B3: Base | C3: Change this dropdown to switch all linked outputs.
A5: Driver | B5: Downside | C5: Base | D5: Upside | E5: Rationale / definition | F5: Selected
A6: Campaign reach | B6: 1200000 | C6: 2000000 | D6: 3000000 | E6: Unique people reached by campaign; illustrative audience reach. | F6: =INDEX(B6:D6,1,MATCH($B$3,$B$5:$D$5,0)) -> 2000000
A7: Engagement rate | B7: 0.08 | C7: 0.12 | D7: 0.15 | E7: Share of reached audience that meaningfully engages. | F7: =INDEX(B7:D7,1,MATCH($B$3,$B$5:$D$5,0)) -> 0.12
A8: Visit rate from engaged | B8: 0.2 | C8: 0.3 | D8: 0.35 | E8: Share of engaged audience that visits a product/site destination. | F8: =INDEX(B8:D8,1,MATCH($B$3,$B$5:$D$5,0)) -> 0.3
A9: Purchase conversion | B9: 0.025 | C9: 0.04 | D9: 0.045 | E9: Share of site visits converting to an order. | F9: =INDEX(B9:D9,1,MATCH($B$3,$B$5:$D$5,0)) -> 0.04
A10: Average order value (INR) | B10: 5500 | C10: 6500 | D10: 7000 | E10: Average revenue per campaign-attributed order. | F10: =INDEX(B10:D10,1,MATCH($B$3,$B$5:$D$5,0)) -> 6500
A11: Gross margin | B11: 0.38 | C11: 0.42 | D11: 0.45 | E11: Illustrative gross margin on campaign-attributed sales. | F11: =INDEX(B11:D11,1,MATCH($B$3,$B$5:$D$5,0)) -> 0.42
A12: Incremental variable costs | B12: 0.1 | C12: 0.08 | D12: 0.07 | E12: Payment, fulfilment, return/service and other incremental variable costs as % revenue. | F12: =INDEX(B12:D12,1,MATCH($B$3,$B$5:$D$5,0)) -> 0.08
A13: Campaign investment (INR) | B13: 10000000 | C13: 10000000 | D13: 10000000 | E13: Fixed campaign budget assumption: ₹1 crore. | F13: =INDEX(B13:D13,1,MATCH($B$3,$B$5:$D$5,0)) -> 10000000
A14: Repeat purchase rate (within model period) | B14: 0.05 | C14: 0.1 | D14: 0.15 | E14: Share of first-order customers assumed to place one additional order in period. | F14: =INDEX(B14:D14,1,MATCH($B$3,$B$5:$D$5,0)) -> 0.1
A16: Selected value | B16: Formula-linked scenario input
A17: Contribution margin | F17: =F11-F12 -> 0.34
A18: First orders | F18: =F6*F7*F8*F9 -> 2880
A19: Total orders incl. repeat | F19: =F18*(1+F14) -> 3168
A20: Revenue | F20: =F19*F10 -> 20592000
A21: Contribution | F21: =F20*F17 -> 7001280
A22: Net contribution after campaign | F22: =F21-F13 -> -2998720

Sheet Scenario Analysis
A1: SCENARIO ANALYSIS
A3: Metric | B3: Downside | C3: Base | D3: Upside | E3: Unit | F3: Formula / interpretation | G3: Selected case
A4: Reach | B4: =Inputs!B6 -> 1200000 | C4: =Inputs!C6 -> 2000000 | D4: =Inputs!D6 -> 3000000 | E4: people | F4: Campaign reach | G4: =INDEX(B4:D4,1,MATCH(Inputs!$B$3,$B$3:$D$3,0)) -> 2000000
A5: Engaged audience | B5: =Inputs!B6*Inputs!B7 -> 96000 | C5: =Inputs!C6*Inputs!C7 -> 240000 | D5: =Inputs!D6*Inputs!D7 -> 450000 | E5: people | F5: Reach × engagement rate | G5: =INDEX(B5:D5,1,MATCH(Inputs!$B$3,$B$3:$D$3,0)) -> 240000
A6: Site visits | B6: =Inputs!B6*Inputs!B7*Inputs!B8 -> 19200 | C6: =Inputs!C6*Inputs!C7*Inputs!C8 -> 72000 | D6: =Inputs!D6*Inputs!D7*Inputs!D8 -> 157500 | E6: visits | F6: Engaged audience × visit rate | G6: =INDEX(B6:D6,1,MATCH(Inputs!$B$3,$B$3:$D$3,0)) -> 72000
A7: First orders | B7: =Inputs!B6*Inputs!B7*Inputs!B8*Inputs!B9 -> 480 | C7: =Inputs!C6*Inputs!C7*Inputs!C8*Inputs!C9 -> 2880 | D7: =Inputs!D6*Inputs!D7*Inputs!D8*Inputs!D9 -> 7087.5 | E7: orders | F7: Site visits × purchase conversion | G7: =INDEX(B7:D7,1,MATCH(Inputs!$B$3,$B$3:$D$3,0)) -> 2880
A8: Repeat orders | B8: =Inputs!B6*Inputs!B7*Inputs!B8*Inputs!B9*Inputs!B14 -> 24 | C8: =Inputs!C6*Inputs!C7*Inputs!C8*Inputs!C9*Inputs!C14 -> 288 | D8: =Inputs!D6*Inputs!D7*Inputs!D8*Inputs!D9*Inputs!D14 -> 1063.125 | E8: orders | F8: First orders × repeat purchase rate | G8: =INDEX(B8:D8,1,MATCH(Inputs!$B$3,$B$3:$D$3,0)) -> 288
A9: Total orders | B9: =Inputs!B6*Inputs!B7*Inputs!B8*Inputs!B9*(1+Inputs!B14) -> 504 | C9: =Inputs!C6*Inputs!C7*Inputs!C8*Inputs!C9*(1+Inputs!C14) -> 3168 | D9: =Inputs!D6*Inputs!D7*Inputs!D8*Inputs!D9*(1+Inputs!D14) -> 8150.625 | E9: orders | F9: First orders + repeat orders | G9: =INDEX(B9:D9,1,MATCH(Inputs!$B$3,$B$3:$D$3,0)) -> 3168
A10: Revenue | B10: =Inputs!B6*Inputs!B7*Inputs!B8*Inputs!B9*(1+Inputs!B14)*Inputs!B10 -> 2772000 | C10: =Inputs!C6*Inputs!C7*Inputs!C8*Inputs!C9*(1+Inputs!C14)*Inputs!C10 -> 20592000 | D10: =Inputs!D6*Inputs!D7*Inputs!D8*Inputs!D9*(1+Inputs!D14)*Inputs!D10 -> 57054375 | E10: INR | F10: Total orders × average order value | G10: =INDEX(B10:D10,1,MATCH(Inputs!$B$3,$B$3:$D$3,0)) -> 20592000
A11: Gross profit | B11: =Inputs!B6*Inputs!B7*Inputs!B8*Inputs!B9*(1+Inputs!B14)*Inputs!B10*Inputs!B11 -> 1053360 | C11: =Inputs!C6*Inputs!C7*Inputs!C8*Inputs!C9*(1+Inputs!C14)*Inputs!C10*Inputs!C11 -> 8648640 | D11: =Inputs!D6*Inputs!D7*Inputs!D8*Inputs!D9*(1+Inputs!D14)*Inputs!D10*Inputs!D11 -> 25674469 | E11: INR | F11: Revenue × gross margin | G11: =INDEX(B11:D11,1,MATCH(Inputs!$B$3,$B$3:$D$3,0)) -> 8648640
A12: Variable costs | B12: =Inputs!B6*Inputs!B7*Inputs!B8*Inputs!B9*(1+Inputs!B14)*Inputs!B10*Inputs!B12 -> 277200 | C12: =Inputs!C6*Inputs!C7*Inputs!C8*Inputs!C9*(1+Inputs!C14)*Inputs!C10*Inputs!C12 -> 1647360 | D12: =Inputs!D6*Inputs!D7*Inputs!D8*Inputs!D9*(1+Inputs!D14)*Inputs!D10*Inputs!D12 -> 3993806.2 | E12: INR | F12: Revenue × incremental variable costs | G12: =INDEX(B12:D12,1,MATCH(Inputs!$B$3,$B$3:$D$3,0)) -> 1647360
A13: Contribution | B13: =Inputs!B6*Inputs!B7*Inputs!B8*Inputs!B9*(1+Inputs!B14)*Inputs!B10*(Inputs!B11-Inputs!B12) -> 776160 | C13: =Inputs!C6*Inputs!C7*Inputs!C8*Inputs!C9*(1+Inputs!C14)*Inputs!C10*(Inputs!C11-Inputs!C12) -> 7001280 | D13: =Inputs!D6*Inputs!D7*Inputs!D8*Inputs!D9*(1+Inputs!D14)*Inputs!D10*(Inputs!D11-Inputs!D12) -> 21680662 | E13: INR | F13: Gross profit − variable costs | G13: =INDEX(B13:D13,1,MATCH(Inputs!$B$3,$B$3:$D$3,0)) -> 7001280
A14: Campaign investment | B14: =Inputs!B13 -> 10000000 | C14: =Inputs!C13 -> 10000000 | D14: =Inputs!D13 -> 10000000 | E14: INR | F14: Fixed campaign budget | G14: =INDEX(B14:D14,1,MATCH(Inputs!$B$3,$B$3:$D$3,0)) -> 10000000
A15: Net contribution after campaign | B15: =Inputs!B6*Inputs!B7*Inputs!B8*Inputs!B9*(1+Inputs!B14)*Inputs!B10*(Inputs!B11-Inputs!B12)-Inputs!B13 -> -9223840 | C15: =Inputs!C6*Inputs!C7*Inputs!C8*Inputs!C9*(1+Inputs!C14)*Inputs!C10*(Inputs!C11-Inputs!C12)-Inputs!C13 -> -2998720 | D15: =Inputs!D6*Inputs!D7*Inputs!D8*Inputs!D9*(1+Inputs!D14)*Inputs!D10*(Inputs!D11-Inputs!D12)-Inputs!D13 -> 11680662 | E15: INR | F15: Contribution − campaign investment | G15: =INDEX(B15:D15,1,MATCH(Inputs!$B$3,$B$3:$D$3,0)) -> -2998720
A16: Contribution per order | B16: =Inputs!B10*(Inputs!B11-Inputs!B12) -> 1540 | C16: =Inputs!C10*(Inputs!C11-Inputs!C12) -> 2210 | D16: =Inputs!D10*(Inputs!D11-Inputs!D12) -> 2660 | E16: INR/order | F16: Contribution ÷ total orders | G16: =INDEX(B16:D16,1,MATCH(Inputs!$B$3,$B$3:$D$3,0)) -> 2210
A17: Break-even orders | B17: =IFERROR(Inputs!B13/(Inputs!B10*(Inputs!B11-Inputs!B12)),0) -> 6493.5065 | C17: =IFERROR(Inputs!C13/(Inputs!C10*(Inputs!C11-Inputs!C12)),0) -> 4524.8869 | D17: =IFERROR(Inputs!D13/(Inputs!D10*(Inputs!D11-Inputs!D12)),0) -> 3759.3985 | E17: orders | F17: Campaign investment ÷ contribution per order | G17: =INDEX(B17:D17,1,MATCH(Inputs!$B$3,$B$3:$D$3,0)) -> 4524.8869
A18: Campaign cost per first order | B18: =IFERROR(Inputs!B13/(Inputs!B6*Inputs!B7*Inputs!B8*Inputs!B9),0) -> 20833.333 | C18: =IFERROR(Inputs!C13/(Inputs!C6*Inputs!C7*Inputs!C8*Inputs!C9),0) -> 3472.2222 | D18: =IFERROR(Inputs!D13/(Inputs!D6*Inputs!D7*Inputs!D8*Inputs!D9),0) -> 1410.9347 | E18: INR/order | F18: Campaign investment ÷ first orders | G18: =INDEX(B18:D18,1,MATCH(Inputs!$B$3,$B$3:$D$3,0)) -> 3472.2222
A19: Contribution return on campaign spend | B19: =IFERROR((Inputs!B6*Inputs!B7*Inputs!B8*Inputs!B9*(1+Inputs!B14)*Inputs!B10*(Inputs!B11-Inputs!B12))/Inputs!B13,0) -> 0.077616 | C19: =IFERROR((Inputs!C6*Inputs!C7*Inputs!C8*Inputs!C9*(1+Inputs!C14)*Inputs!C10*(Inputs!C11-Inputs!C12))/Inputs!C13,0) -> 0.700128 | D19: =IFERROR((Inputs!D6*Inputs!D7*Inputs!D8*Inputs!D9*(1+Inputs!D14)*Inputs!D10*(Inputs!D11-Inputs!D12))/Inputs!D13,0) -> 2.1680662 | E19: x | F19: Contribution ÷ campaign investment | G19: =INDEX(B19:D19,1,MATCH(Inputs!$B$3,$B$3:$D$3,0)) -> 0.700128
A21: Scenario | B21: Downside | C21: Base | D21: Upside
A22: Net contribution | B22: =B15 -> -9223840 | C22: =C15 -> -2998720 | D22: =D15 -> 11680662

Sheet 12-Month Model
A1: 12-MONTH CAMPAIGN PHASING
A2: Selected scenario is linked from Inputs. Monthly phasing weights are editable; default weights sum to 100%.
A4: Month | B4: Phasing weight | C4: Reach | D4: Engaged | E4: Visits | F4: First orders | G4: Repeat orders | H4: Revenue | I4: Contribution after campaign spend
A5: Month 1 | B5: 0.06 | C5: =Inputs!$F$6*B5 -> 120000 | D5: =C5*Inputs!$F$7 -> 14400 | E5: =D5*Inputs!$F$8 -> 4320 | F5: =E5*Inputs!$F$9 -> 172.8 | G5: =F5*Inputs!$F$14 -> 17.28 | H5: =(F5+G5)*Inputs!$F$10 -> 1235520 | I5: =H5*Inputs!$F$17-Inputs!$F$13*B5 -> -179923.2
A6: Month 2 | B6: 0.06 | C6: =Inputs!$F$6*B6 -> 120000 | D6: =C6*Inputs!$F$7 -> 14400 | E6: =D6*Inputs!$F$8 -> 4320 | F6: =E6*Inputs!$F$9 -> 172.8 | G6: =F6*Inputs!$F$14 -> 17.28 | H6: =(F6+G6)*Inputs!$F$10 -> 1235520 | I6: =H6*Inputs!$F$17-Inputs!$F$13*B6 -> -179923.2
A7: Month 3 | B7: 0.07 | C7: =Inputs!$F$6*B7 -> 140000 | D7: =C7*Inputs!$F$7 -> 16800 | E7: =D7*Inputs!$F$8 -> 5040 | F7: =E7*Inputs!$F$9 -> 201.6 | G7: =F7*Inputs!$F$14 -> 20.16 | H7: =(F7+G7)*Inputs!$F$10 -> 1441440 | I7: =H7*Inputs!$F$17-Inputs!$F$13*B7 -> -209910.4
A8: Month 4 | B8: 0.08 | C8: =Inputs!$F$6*B8 -> 160000 | D8: =C8*Inputs!$F$7 -> 19200 | E8: =D8*Inputs!$F$8 -> 5760 | F8: =E8*Inputs!$F$9 -> 230.4 | G8: =F8*Inputs!$F$14 -> 23.04 | H8: =(F8+G8)*Inputs!$F$10 -> 1647360 | I8: =H8*Inputs!$F$17-Inputs!$F$13*B8 -> -239897.6
A9: Month 5 | B9: 0.08 | C9: =Inputs!$F$6*B9 -> 160000 | D9: =C9*Inputs!$F$7 -> 19200 | E9: =D9*Inputs!$F$8 -> 5760 | F9: =E9*Inputs!$F$9 -> 230.4 | G9: =F9*Inputs!$F$14 -> 23.04 | H9: =(F9+G9)*Inputs!$F$10 -> 1647360 | I9: =H9*Inputs!$F$17-Inputs!$F$13*B9 -> -239897.6
A10: Month 6 | B10: 0.09 | C10: =Inputs!$F$6*B10 -> 180000 | D10: =C10*Inputs!$F$7 -> 21600 | E10: =D10*Inputs!$F$8 -> 6480 | F10: =E10*Inputs!$F$9 -> 259.2 | G10: =F10*Inputs!$F$14 -> 25.92 | H10: =(F10+G10)*Inputs!$F$10 -> 1853280 | I10: =H10*Inputs!$F$17-Inputs!$F$13*B10 -> -269884.8
A11: Month 7 | B11: 0.09 | C11: =Inputs!$F$6*B11 -> 180000 | D11: =C11*Inputs!$F$7 -> 21600 | E11: =D11*Inputs!$F$8 -> 6480 | F11: =E11*Inputs!$F$9 -> 259.2 | G11: =F11*Inputs!$F$14 -> 25.92 | H11: =(F11+G11)*Inputs!$F$10 -> 1853280 | I11: =H11*Inputs!$F$17-Inputs!$F$13*B11 -> -269884.8
A12: Month 8 | B12: 0.09 | C12: =Inputs!$F$6*B12 -> 180000 | D12: =C12*Inputs!$F$7 -> 21600 | E12: =D12*Inputs!$F$8 -> 6480 | F12: =E12*Inputs!$F$9 -> 259.2 | G12: =F12*Inputs!$F$14 -> 25.92 | H12: =(F12+G12)*Inputs!$F$10 -> 1853280 | I12: =H12*Inputs!$F$17-Inputs!$F$13*B12 -> -269884.8
A13: Month 9 | B13: 0.1 | C13: =Inputs!$F$6*B13 -> 200000 | D13: =C13*Inputs!$F$7 -> 24000 | E13: =D13*Inputs!$F$8 -> 7200 | F13: =E13*Inputs!$F$9 -> 288 | G13: =F13*Inputs!$F$14 -> 28.8 | H13: =(F13+G13)*Inputs!$F$10 -> 2059200 | I13: =H13*Inputs!$F$17-Inputs!$F$13*B13 -> -299872
A14: Month 10 | B14: 0.1 | C14: =Inputs!$F$6*B14 -> 200000 | D14: =C14*Inputs!$F$7 -> 24000 | E14: =D14*Inputs!$F$8 -> 7200 | F14: =E14*Inputs!$F$9 -> 288 | G14: =F14*Inputs!$F$14 -> 28.8 | H14: =(F14+G14)*Inputs!$F$10 -> 2059200 | I14: =H14*Inputs!$F$17-Inputs!$F$13*B14 -> -299872
A15: Month 11 | B15: 0.09 | C15: =Inputs!$F$6*B15 -> 180000 | D15: =C15*Inputs!$F$7 -> 21600 | E15: =D15*Inputs!$F$8 -> 6480 | F15: =E15*Inputs!$F$9 -> 259.2 | G15: =F15*Inputs!$F$14 -> 25.92 | H15: =(F15+G15)*Inputs!$F$10 -> 1853280 | I15: =H15*Inputs!$F$17-Inputs!$F$13*B15 -> -269884.8
A16: Month 12 | B16: 0.09 | C16: =Inputs!$F$6*B16 -> 180000 | D16: =C16*Inputs!$F$7 -> 21600 | E16: =D16*Inputs!$F$8 -> 6480 | F16: =E16*Inputs!$F$9 -> 259.2 | G16: =F16*Inputs!$F$14 -> 25.92 | H16: =(F16+G16)*Inputs!$F$10 -> 1853280 | I16: =H16*Inputs!$F$17-Inputs!$F$13*B16 -> -269884.8
A17: Total | B17: =SUM(B5:B16) -> 1 | C17: =SUM(C5:C16) -> 2000000 | D17: =SUM(D5:D16) -> 240000 | E17: =SUM(E5:E16) -> 72000 | F17: =SUM(F5:F16) -> 2880 | G17: =SUM(G5:G16) -> 288 | H17: =SUM(H5:H16) -> 20592000 | I17: =SUM(I5:I16) -> -2998720
A19: Phasing check | B19: =IF(ABS(B17-1)<0.000001,"PASS — weights total 100%","CHECK — weights must total 100%") -> PASS — weights total 100%

Sheet Sensitivity
A1: SENSITIVITY — NET CONTRIBUTION AFTER CAMPAIGN
A2: Illustrative sensitivity using selected engagement, visit rate, AOV, contribution margin, repeat rate and investment; vary reach and purchase conversion.
A4: Reach \ Conversion | B4: 0.02 | C4: 0.025 | D4: 0.03 | E4: 0.035 | F4: 0.04 | G4: 0.045 | H4: 0.05
A5: 1000000 | B5: =($A5*Inputs!$F$7*Inputs!$F$8*B$4*(1+Inputs!$F$14)*Inputs!$F$10*Inputs!$F$17)-Inputs!$F$13 -> -8249680 | C5: =($A5*Inputs!$F$7*Inputs!$F$8*C$4*(1+Inputs!$F$14)*Inputs!$F$10*Inputs!$F$17)-Inputs!$F$13 -> -7812100 | D5: =($A5*Inputs!$F$7*Inputs!$F$8*D$4*(1+Inputs!$F$14)*Inputs!$F$10*Inputs!$F$17)-Inputs!$F$13 -> -7374520 | E5: =($A5*Inputs!$F$7*Inputs!$F$8*E$4*(1+Inputs!$F$14)*Inputs!$F$10*Inputs!$F$17)-Inputs!$F$13 -> -6936940 | F5: =($A5*Inputs!$F$7*Inputs!$F$8*F$4*(1+Inputs!$F$14)*Inputs!$F$10*Inputs!$F$17)-Inputs!$F$13 -> -6499360 | G5: =($A5*Inputs!$F$7*Inputs!$F$8*G$4*(1+Inputs!$F$14)*Inputs!$F$10*Inputs!$F$17)-Inputs!$F$13 -> -6061780 | H5: =($A5*Inputs!$F$7*Inputs!$F$8*H$4*(1+Inputs!$F$14)*Inputs!$F$10*Inputs!$F$17)-Inputs!$F$13 -> -5624200
A6: 1500000 | B6: =($A6*Inputs!$F$7*Inputs!$F$8*B$4*(1+Inputs!$F$14)*Inputs!$F$10*Inputs!$F$17)-Inputs!$F$13 -> -7374520 | C6: =($A6*Inputs!$F$7*Inputs!$F$8*C$4*(1+Inputs!$F$14)*Inputs!$F$10*Inputs!$F$17)-Inputs!$F$13 -> -6718150 | D6: =($A6*Inputs!$F$7*Inputs!$F$8*D$4*(1+Inputs!$F$14)*Inputs!$F$10*Inputs!$F$17)-Inputs!$F$13 -> -6061780 | E6: =($A6*Inputs!$F$7*Inputs!$F$8*E$4*(1+Inputs!$F$14)*Inputs!$F$10*Inputs!$F$17)-Inputs!$F$13 -> -5405410 | F6: =($A6*Inputs!$F$7*Inputs!$F$8*F$4*(1+Inputs!$F$14)*Inputs!$F$10*Inputs!$F$17)-Inputs!$F$13 -> -4749040 | G6: =($A6*Inputs!$F$7*Inputs!$F$8*G$4*(1+Inputs!$F$14)*Inputs!$F$10*Inputs!$F$17)-Inputs!$F$13 -> -4092670 | H6: =($A6*Inputs!$F$7*Inputs!$F$8*H$4*(1+Inputs!$F$14)*Inputs!$F$10*Inputs!$F$17)-Inputs!$F$13 -> -3436300
A7: 2000000 | B7: =($A7*Inputs!$F$7*Inputs!$F$8*B$4*(1+Inputs!$F$14)*Inputs!$F$10*Inputs!$F$17)-Inputs!$F$13 -> -6499360 | C7: =($A7*Inputs!$F$7*Inputs!$F$8*C$4*(1+Inputs!$F$14)*Inputs!$F$10*Inputs!$F$17)-Inputs!$F$13 -> -5624200 | D7: =($A7*Inputs!$F$7*Inputs!$F$8*D$4*(1+Inputs!$F$14)*Inputs!$F$10*Inputs!$F$17)-Inputs!$F$13 -> -4749040 | E7: =($A7*Inputs!$F$7*Inputs!$F$8*E$4*(1+Inputs!$F$14)*Inputs!$F$10*Inputs!$F$17)-Inputs!$F$13 -> -3873880 | F7: =($A7*Inputs!$F$7*Inputs!$F$8*F$4*(1+Inputs!$F$14)*Inputs!$F$10*Inputs!$F$17)-Inputs!$F$13 -> -2998720 | G7: =($A7*Inputs!$F$7*Inputs!$F$8*G$4*(1+Inputs!$F$14)*Inputs!$F$10*Inputs!$F$17)-Inputs!$F$13 -> -2123560 | H7: =($A7*Inputs!$F$7*Inputs!$F$8*H$4*(1+Inputs!$F$14)*Inputs!$F$10*Inputs!$F$17)-Inputs!$F$13 -> -1248400
A8: 2500000 | B8: =($A8*Inputs!$F$7*Inputs!$F$8*B$4*(1+Inputs!$F$14)*Inputs!$F$10*Inputs!$F$17)-Inputs!$F$13 -> -5624200 | C8: =($A8*Inputs!$F$7*Inputs!$F$8*C$4*(1+Inputs!$F$14)*Inputs!$F$10*Inputs!$F$17)-Inputs!$F$13 -> -4530250 | D8: =($A8*Inputs!$F$7*Inputs!$F$8*D$4*(1+Inputs!$F$14)*Inputs!$F$10*Inputs!$F$17)-Inputs!$F$13 -> -3436300 | E8: =($A8*Inputs!$F$7*Inputs!$F$8*E$4*(1+Inputs!$F$14)*Inputs!$F$10*Inputs!$F$17)-Inputs!$F$13 -> -2342350 | F8: =($A8*Inputs!$F$7*Inputs!$F$8*F$4*(1+Inputs!$F$14)*Inputs!$F$10*Inputs!$F$17)-Inputs!$F$13 -> -1248400 | G8: =($A8*Inputs!$F$7*Inputs!$F$8*G$4*(1+Inputs!$F$14)*Inputs!$F$10*Inputs!$F$17)-Inputs!$F$13 -> -154450 | H8: =($A8*Inputs!$F$7*Inputs!$F$8*H$4*(1+Inputs!$F$14)*Inputs!$F$10*Inputs!$F$17)-Inputs!$F$13 -> 939500
A9: 3000000 | B9: =($A9*Inputs!$F$7*Inputs!$F$8*B$4*(1+Inputs!$F$14)*Inputs!$F$10*Inputs!$F$17)-Inputs!$F$13 -> -4749040 | C9: =($A9*Inputs!$F$7*Inputs!$F$8*C$4*(1+Inputs!$F$14)*Inputs!$F$10*Inputs!$F$17)-Inputs!$F$13 -> -3436300 | D9: =($A9*Inputs!$F$7*Inputs!$F$8*D$4*(1+Inputs!$F$14)*Inputs!$F$10*Inputs!$F$17)-Inputs!$F$13 -> -2123560 | E9: =($A9*Inputs!$F$7*Inputs!$F$8*E$4*(1+Inputs!$F$14)*Inputs!$F$10*Inputs!$F$17)-Inputs!$F$13 -> -810820 | F9: =($A9*Inputs!$F$7*Inputs!$F$8*F$4*(1+Inputs!$F$14)*Inputs!$F$10*Inputs!$F$17)-Inputs!$F$13 -> 501920 | G9: =($A9*Inputs!$F$7*Inputs!$F$8*G$4*(1+Inputs!$F$14)*Inputs!$F$10*Inputs!$F$17)-Inputs!$F$13 -> 1814660 | H9: =($A9*Inputs!$F$7*Inputs!$F$8*H$4*(1+Inputs!$F$14)*Inputs!$F$10*Inputs!$F$17)-Inputs!$F$13 -> 3127400
A10: 3500000 | B10: =($A10*Inputs!$F$7*Inputs!$F$8*B$4*(1+Inputs!$F$14)*Inputs!$F$10*Inputs!$F$17)-Inputs!$F$13 -> -3873880 | C10: =($A10*Inputs!$F$7*Inputs!$F$8*C$4*(1+Inputs!$F$14)*Inputs!$F$10*Inputs!$F$17)-Inputs!$F$13 -> -2342350 | D10: =($A10*Inputs!$F$7*Inputs!$F$8*D$4*(1+Inputs!$F$14)*Inputs!$F$10*Inputs!$F$17)-Inputs!$F$13 -> -810820 | E10: =($A10*Inputs!$F$7*Inputs!$F$8*E$4*(1+Inputs!$F$14)*Inputs!$F$10*Inputs!$F$17)-Inputs!$F$13 -> 720710 | F10: =($A10*Inputs!$F$7*Inputs!$F$8*F$4*(1+Inputs!$F$14)*Inputs!$F$10*Inputs!$F$17)-Inputs!$F$13 -> 2252240 | G10: =($A10*Inputs!$F$7*Inputs!$F$8*G$4*(1+Inputs!$F$14)*Inputs!$F$10*Inputs!$F$17)-Inputs!$F$13 -> 3783770 | H10: =($A10*Inputs!$F$7*Inputs!$F$8*H$4*(1+Inputs!$F$14)*Inputs!$F$10*Inputs!$F$17)-Inputs!$F$13 -> 5315300
A12: Interpretation | B12: Cells show contribution after campaign investment, not net profit. Negative values mean campaign-attributed contribution does not recover the campaign budget under that combination.

Sheet Dashboard
A1: NIKE GEN Z INDIA — FINANCIAL DASHBOARD
A3: Selected scenario | B3: =Inputs!B3 -> Base
A5: Campaign reach | B5: ='Scenario Analysis'!G4 -> 2000000 | C5: people
A6: First orders | B6: ='Scenario Analysis'!G7 -> 2880 | C6: orders
A7: Total orders incl. repeat | B7: ='Scenario Analysis'!G9 -> 3168 | C7: orders
A8: Revenue | B8: ='Scenario Analysis'!G10 -> 20592000 | C8: INR
A9: Contribution | B9: ='Scenario Analysis'!G13 -> 7001280 | C9: INR
A10: Campaign investment | B10: ='Scenario Analysis'!G14 -> 10000000 | C10: INR
A11: Net contribution after campaign | B11: ='Scenario Analysis'!G15 -> -2998720 | C11: INR
A12: Break-even orders | B12: ='Scenario Analysis'!G17 -> 4524.8869 | C12: orders
A13: Campaign cost per first order | B13: ='Scenario Analysis'!G18 -> 3472.2222 | C13: INR/order
A14: Contribution return on campaign spend | B14: ='Scenario Analysis'!G19 -> 0.700128 | C14: x
A17: Decision lens | B17: Use this model to test assumptions and identify the conditions needed to recover campaign investment. A positive contribution result is not the same as net profit or proof of causal impact.
